mkdocs_conditional_include/__init__.py
mkdocs_conditional_include/plugin.py
mkdocs_conditional_include-0.0.1.dist-info/LICENSE
mkdocs_conditional_include-0.0.1.dist-info/METADATA
mkdocs_conditional_include-0.0.1.dist-info/WHEEL
mkdocs_conditional_include-0.0.1.dist-info/entry_points.txt
mkdocs_conditional_include-0.0.1.dist-info/top_level.txt
mkdocs_conditional_include-0.0.1.dist-info/RECORD
