Metadata-Version: 2.1
Name: mkdocs-conditional-include
Version: 0.0.1
Summary: A mkdocs plugin that lets you conditionally include files or trees.
Home-page: https://github.com/KaiReichart/mkdocs-conditional-include
Author: Kai Reichart
Author-email: kai@reichart.dev
License: Apache
Platform: UNKNOWN
License-File: LICENSE
Requires-Dist: mkdocs
